doiit/__init__.py
doiit/utils.py
doiit-0.1.4.dist-info/DESCRIPTION.rst
doiit-0.1.4.dist-info/entry_points.txt
doiit-0.1.4.dist-info/METADATA
doiit-0.1.4.dist-info/metadata.json
doiit-0.1.4.dist-info/RECORD
doiit-0.1.4.dist-info/top_level.txt
doiit-0.1.4.dist-info/WHEEL
