Metadata-Version: 2.0
Name: doiit
Version: 0.1.4
Summary: UNKNOWN
Home-page: https://github.com/wooparadog/doiit
Author: Haochuan Guo
Author-email: guohaochuan@gmail.com
License: BSD
Platform: UNKNOWN
Requires-Dist: click
